convertapi/__init__.py
convertapi/api.py
convertapi/client.py
convertapi/exceptions.py
convertapi/file_param.py
convertapi/format_detector.py
convertapi/result.py
convertapi/result_file.py
convertapi/task.py
convertapi/upload_io.py
convertapi/utils.py
convertapi-2.0.0.dist-info/LICENSE.txt
convertapi-2.0.0.dist-info/METADATA
convertapi-2.0.0.dist-info/WHEEL
convertapi-2.0.0.dist-info/top_level.txt
convertapi-2.0.0.dist-info/RECORD
