Metadata-Version: 2.1
Name: convertapi
Version: 2.0.0
Summary: Convert API Python Client
Home-page: https://github.com/ConvertAPI/convertapi-python
Download-URL: https://github.com/ConvertAPI/convertapi-python
Author: Tomas Rutkauskas
Author-email: support@convertapi.com
License: MIT
Keywords: convert,api,client,conversion
License-File: LICENSE.txt
Requires-Dist: requests>=2.4.2
